CODE_OF_CONDUCT.md
CONTRIBUTING.md
LICENSE.txt
README.md
qiskit_aqt_provider/__init__.py
qiskit_aqt_provider/api_models.py
qiskit_aqt_provider/api_models_generated.py
qiskit_aqt_provider/aqt_job.py
qiskit_aqt_provider/aqt_options.py
qiskit_aqt_provider/aqt_provider.py
qiskit_aqt_provider/aqt_resource.py
qiskit_aqt_provider/circuit_to_aqt.py
qiskit_aqt_provider/primitives/__init__.py
qiskit_aqt_provider/primitives/estimator.py
qiskit_aqt_provider/primitives/sampler.py
qiskit_aqt_provider/py.typed
qiskit_aqt_provider/test/__init__.py
qiskit_aqt_provider/test/circuits.py
qiskit_aqt_provider/test/fixtures.py
qiskit_aqt_provider/test/resources.py
qiskit_aqt_provider/test/timeout.py
qiskit_aqt_provider/transpiler_plugin.py
qiskit_aqt_provider/utils.py
qiskit_aqt_provider/versions.py
qiskit_aqt_provider_rc-0.16.0.dist-info/LICENSE.txt
qiskit_aqt_provider_rc-0.16.0.dist-info/METADATA
qiskit_aqt_provider_rc-0.16.0.dist-info/WHEEL
qiskit_aqt_provider_rc-0.16.0.dist-info/entry_points.txt
qiskit_aqt_provider_rc-0.16.0.dist-info/RECORD
